coastpy/__init__.py
coastpy/_version.py
coastpy/eo/__init__.py
coastpy/eo/band_statistics.py
coastpy/eo/collection.py
coastpy/eo/filter.py
coastpy/eo/indices.py
coastpy/eo/mask.py
coastpy/eo/scalers.py
coastpy/eo/transforms.py
coastpy/eo/typology.py
coastpy/eo/utils.py
coastpy/eo/viz.py
coastpy/geo/__init__.py
coastpy/geo/geoms.py
coastpy/geo/ops.py
coastpy/geo/quadtiles.py
coastpy/geo/quadtiles_utils.py
coastpy/geo/size.py
coastpy/geo/transect.py
coastpy/geo/transform.py
coastpy/geo/utils.py
coastpy/io/__init__.py
coastpy/io/cloud.py
coastpy/io/data.py
coastpy/io/engine.py
coastpy/io/partitioner.py
coastpy/io/utils.py
coastpy/libs/__init__.py
coastpy/libs/stac_table.py
coastpy/stac/__init__.py
coastpy/stac/item.py
coastpy/stac/layouts.py
coastpy/stac/utils.py
coastpy/stats/__init__.py
coastpy/stats/metrics.py
coastpy/utils/__init__.py
coastpy/utils/config.py
coastpy/utils/dask_utils.py
coastpy/utils/grid.py
coastpy/utils/log.py
coastpy/utils/pandas_utils.py
coastpy/utils/shorelines.py
coastpy/utils/size.py
coastpy/utils/xarray_utils.py
coastpy/viz/__init__.py
coastpy/viz/dashboard.py
coastpy-0.2.5.dist-info/METADATA
coastpy-0.2.5.dist-info/WHEEL
coastpy-0.2.5.dist-info/licenses/LICENSE
coastpy-0.2.5.dist-info/RECORD
