Metadata-Version: 2.4
Name: coastpy
Version: 0.2.5
Summary: Python tools for cloud-native coastal analytics.
Project-URL: Homepage, https://github.com/TUDelft-CITG/coastpy
Author-email: Floris Calkoen <your-email@example.com>
License-Expression: MIT
License-File: LICENSE
Classifier: Development Status :: 4 - Beta
Classifier: Intended Audience :: Developers
Classifier: License :: OSI Approved :: MIT License
Classifier: Programming Language :: Python :: 3
Classifier: Programming Language :: Python :: 3.11
Classifier: Programming Language :: Python :: 3.12
Classifier: Topic :: Scientific/Engineering
Requires-Python: >=3.11
Requires-Dist: antimeridian
Requires-Dist: dask-geopandas
Requires-Dist: dask<2025.3.0
Requires-Dist: duckdb>=1.0.0
Requires-Dist: fsspec
Requires-Dist: geopandas
Requires-Dist: mercantile
Requires-Dist: odc-geo
Requires-Dist: odc-stac
Requires-Dist: pyarrow
Requires-Dist: pyogrio
Requires-Dist: pyproj
Requires-Dist: pystac
Requires-Dist: rioxarray
Requires-Dist: shapely>=2.0.0
